ingot_psql/__init__.py
ingot_psql/bootstrap/__init__.py
ingot_psql/bootstrap/base.py
ingot_psql/bootstrap/scaffolding/__init__.py
ingot_psql/contrib/__init__.py
ingot_psql/scripts/__init__.py
ingot_psql/scripts/ingot_psql.py
ingot_psql/tests/__init__.py
ingot_psql/tests/functionals/__init__.py
ingot_psql/tests/units/__init__.py
ingot_psql/tests/units/bootstrap/__init__.py
ingot_psql/tests/units/bootstrap/test_base.py
ingot_psql/tests/units/contrib/__init__.py
ingot_psql/tests/units/scripts/__init__.py
ingot_psql/tests/units/scripts/test_ingot_psql.py
ingot_psql-0.1.0.dist-info/LICENSE
ingot_psql-0.1.0.dist-info/METADATA
ingot_psql-0.1.0.dist-info/WHEEL
ingot_psql-0.1.0.dist-info/entry_points.txt
ingot_psql-0.1.0.dist-info/top_level.txt
ingot_psql-0.1.0.dist-info/RECORD
