Metadata-Version: 2.1
Name: ingot-psql
Version: 0.1.0
Summary: Provides integration with the PostgresQL DB for Ingots projects
Home-page: https://github.com/ABKorotky/ingot-postgresql.git
Author: Alexander Korotkiy
Author-email: abkorotky@gamil.com
License: UNKNOWN
Platform: UNKNOWN
Classifier: Development Status :: 1 - Planning
Classifier: Environment :: Web Environment
Classifier: Framework :: AsyncIO
Classifier: Intended Audience :: Developers
Classifier: License :: OSI Approved :: GNU General Public License (GPL)
Classifier: Natural Language :: English
Classifier: Operating System :: POSIX
Classifier: Operating System :: POSIX :: Linux
Classifier: Programming Language :: Python
Classifier: Programming Language :: Python :: 3.9
Classifier: Topic :: Internet
License-File: LICENSE
Requires-Dist: ingots (~=0.19.0)
Requires-Dist: ingot-sql (~=0.2.0)
